plover_number_format.py
plover_number_format-1.2.0.dist-info/LICENSE
plover_number_format-1.2.0.dist-info/METADATA
plover_number_format-1.2.0.dist-info/WHEEL
plover_number_format-1.2.0.dist-info/entry_points.txt
plover_number_format-1.2.0.dist-info/top_level.txt
plover_number_format-1.2.0.dist-info/zip-safe
plover_number_format-1.2.0.dist-info/RECORD
