Metadata-Version: 2.1
Name: plover-number-format
Version: 1.2.0
Summary: Formats numbers in the specified format.
Home-page: https://github.com/Volensia/plover_number_format
Author: Volensia
Author-email: howmeng@hotmail.com
License: MIT
Keywords: plover plover_plugin
License-File: LICENSE
Requires-Dist: plover (>=4.0.0.dev11)
